cidownloader/__init__.py
cidownloader/cadastral_inspire_downloader.py
cidownloader/cli.py
catastroinspiredownloader-0.3.1.dist-info/METADATA
catastroinspiredownloader-0.3.1.dist-info/WHEEL
catastroinspiredownloader-0.3.1.dist-info/entry_points.txt
catastroinspiredownloader-0.3.1.dist-info/RECORD
