Metadata-Version: 2.4
Name: CatastroInspireDownloader
Version: 0.3.1
Summary: A CLI tool to download data from Spanish Cadastre Atom Service
Project-URL: Homepage, https://github.com/geomatico/cidownloader
Project-URL: Issues, https://github.com/geomatico/cidownloader/issues
Author-email: Geomatico <info@geomatico.es>
License-Expression: GPL-3.0-or-later
Classifier: Operating System :: OS Independent
Classifier: Programming Language :: Python :: 3
Requires-Python: >=3.9
Requires-Dist: atoma==0.0.17
Requires-Dist: click==7.0
Requires-Dist: requests==2.32.0
